__init__.py
mt_auto_minhon_mlt/__init__.py
mt_auto_minhon_mlt/tranlator.py
mt_auto_minhon_mlt/assets/support_translate.json
mt_auto_minhon_mlt-1.0.3.dist-info/METADATA
mt_auto_minhon_mlt-1.0.3.dist-info/WHEEL
mt_auto_minhon_mlt-1.0.3.dist-info/top_level.txt
mt_auto_minhon_mlt-1.0.3.dist-info/RECORD
