Metadata-Version: 2.1
Name: mt-auto-minhon-mlt
Version: 1.0.3
Summary: みんなの自動翻訳 Python Library
Project-URL: Homepage, https://github.com/MIDORIBIN/mt-auto-minhon-mlt
Project-URL: Bug Tracker, https://github.com/MIDORIBIN/mt-auto-minhon-mlt/issues
Classifier: Programming Language :: Python :: 3
Classifier: Programming Language :: Python :: 3.7
Classifier: Programming Language :: Python :: 3.8
Classifier: Programming Language :: Python :: 3.9
Classifier: Programming Language :: Python :: 3.10
Requires-Python: <3.11,>=3.7
Provides-Extra: dev
Requires-Dist: black ; extra == 'dev'
Requires-Dist: pyproject-flake8 ; extra == 'dev'
